{
  "en": {
    "change_language": "Change language & region",
    "submit": "Submit",

    "hello": "hello",
    "world": "world",
    "products": "Products"
  },
  "de": {
    "change_language": "Sprache und Region ändern",
    "submit": "Einreichen",

    "hello": "hallo",
    "world": "world",
    "products": "Itemes"
  },
  "fr": {
    "change_language": "Changer de langue et de région",
    "submit": "Soumettre",

    "hello": "bonjour",
    "world": "world",
    "products": "Les productes"
  }
}
